allauth_sniperlinks/__init__.py
allauth_sniperlinks/adapter.py
allauth_sniperlinks/admin.py
allauth_sniperlinks/app_settings.py
allauth_sniperlinks/apps.py
allauth_sniperlinks/context_processors.py
allauth_sniperlinks/models.py
allauth_sniperlinks/signals.py
allauth_sniperlinks/tests.py
allauth_sniperlinks/utils.py
allauth_sniperlinks/views.py
allauth_sniperlinks/management/__init__.py
allauth_sniperlinks/management/commands/__init__.py
allauth_sniperlinks/management/commands/clear_sniperlink_cache.py
allauth_sniperlinks/migrations/0001_initial.py
allauth_sniperlinks/migrations/0002_alter_sniperlink_mail_provider.py
allauth_sniperlinks/migrations/__init__.py
allauth_sniperlinks/static/allauth_sniperlinks/provider_icons/AOL.svg
allauth_sniperlinks/static/allauth_sniperlinks/provider_icons/CenturyLink.svg
allauth_sniperlinks/static/allauth_sniperlinks/provider_icons/Charter.svg
allauth_sniperlinks/static/allauth_sniperlinks/provider_icons/Comcast.svg
allauth_sniperlinks/static/allauth_sniperlinks/provider_icons/Cox.svg
allauth_sniperlinks/static/allauth_sniperlinks/provider_icons/Fastmail.svg
allauth_sniperlinks/static/allauth_sniperlinks/provider_icons/Frontier.svg
allauth_sniperlinks/static/allauth_sniperlinks/provider_icons/Gmail.svg
allauth_sniperlinks/static/allauth_sniperlinks/provider_icons/Gsuite.svg
allauth_sniperlinks/static/allauth_sniperlinks/provider_icons/Juno.svg
allauth_sniperlinks/static/allauth_sniperlinks/provider_icons/Mail_com.svg
allauth_sniperlinks/static/allauth_sniperlinks/provider_icons/Outlook.svg
allauth_sniperlinks/static/allauth_sniperlinks/provider_icons/Prodigy.svg
allauth_sniperlinks/static/allauth_sniperlinks/provider_icons/ProtonMail.svg
allauth_sniperlinks/static/allauth_sniperlinks/provider_icons/Rogers.svg
allauth_sniperlinks/static/allauth_sniperlinks/provider_icons/Shaw.svg
allauth_sniperlinks/static/allauth_sniperlinks/provider_icons/Yahoo.svg
allauth_sniperlinks/static/allauth_sniperlinks/provider_icons/generic.svg
django_allauth_sniperlinks-0.3.dist-info/LICENSE
django_allauth_sniperlinks-0.3.dist-info/METADATA
django_allauth_sniperlinks-0.3.dist-info/WHEEL
django_allauth_sniperlinks-0.3.dist-info/top_level.txt
django_allauth_sniperlinks-0.3.dist-info/RECORD
