Metadata-Version: 2.1
Name: django-allauth-sniperlinks
Version: 0.3
Summary: A Django app to provide sniper links for allauth email verification.
Home-page: https://github.com/skulegirl/django-allauth-sniperlinks
Author: Anna Maste
Author-email: anna@subscribesense.com
License: MIT
Classifier: Environment :: Web Environment
Classifier: Framework :: Django
Classifier: Framework :: Django :: 3.2
Classifier: Intended Audience :: Developers
Classifier: License :: OSI Approved :: MIT License
Classifier: Operating System :: OS Independent
Classifier: Programming Language :: Python
Classifier: Programming Language :: Python :: 3
Classifier: Programming Language :: Python :: 3 :: Only
Classifier: Programming Language :: Python :: 3.6
Classifier: Programming Language :: Python :: 3.7
Classifier: Programming Language :: Python :: 3.8
Classifier: Topic :: Internet
Classifier: Topic :: Software Development :: Libraries :: Python Modules
Requires-Python: >=3.6
License-File: LICENSE
Requires-Dist: Django (>=3.2)
Requires-Dist: django-allauth (>=0.41.0)
Requires-Dist: tld (>=0.12.6)
Requires-Dist: dnspython (>=2.2.0)
